pyfacy_dlib_models/__init__.py
pyfacy_dlib_models/dlib_models/dlib_face_recognition_resnet_model_v1.dat
pyfacy_dlib_models/dlib_models/mmod_human_face_detector.dat
pyfacy_dlib_models/dlib_models/shape_predictor_5_face_landmarks.dat
pyfacy_dlib_models-0.0.4.dist-info/METADATA
pyfacy_dlib_models-0.0.4.dist-info/RECORD
pyfacy_dlib_models-0.0.4.dist-info/WHEEL
pyfacy_dlib_models-0.0.4.dist-info/top_level.txt
